{
  "id": "19",
  "expansion": "A1a",
  "image": "https://limitlesstcg.nyc3.cdn.digitaloceanspaces.com/pocket/A1a/A1a_019_EN.webp",
  "name": "Vaporeon",
  "card_type": "Pokémon",
  "artist": "LINNE",
  "attacks": [
    {
      "name": "Wave",
      "cost": "WCC",
      "effect": "",
      "damage": 60,
      "damage_min": null,
      "damage_mult": null
    }
  ],
  "rarity": "◊◊◊",
  "color": "Water",
  "life": 120,
  "ability": {
    "name": "Wash Out",
    "effect": "As often as you like during your turn, you may move a [W] Energy from 1 of your Benched [W] Pokémon to your Active [W] Pokémon."
  },
  "weakness": "Lightning",
  "retreat_cost": 2
}